setup.py
bin/cell-acceptance-load-calc
cell_acceptance/__init__.py
cell_acceptance/server.py
cell_acceptance.egg-info/PKG-INFO
cell_acceptance.egg-info/SOURCES.txt
cell_acceptance.egg-info/dependency_links.txt
cell_acceptance.egg-info/entry_points.txt
cell_acceptance.egg-info/not-zip-safe
cell_acceptance.egg-info/requires.txt
cell_acceptance.egg-info/top_level.txt
cell_acceptance/oosheet/__init__.py
cell_acceptance/oosheet/columns.py