Metadata-Version: 1.0
Name: cell-acceptance
Version: 0.2.6
Summary: LibreOffice Calc Calculation Engine
Home-page: https://bitbucket.org/MalucoMarinero/cellacceptance
Author: James Rakich
Author-email: james@fullandbydesign.com.au
License: MIT License
Keywords: testing
Platform: UNKNOWN
